{
	"cellSize" : "5",
	"floorThreshold" : "5",
	"monsters" : {
		"piere" : [
			235,185,155,
			150,170,115,
			155,175,125,
			 75, 70, 50,
			 80, 90, 65
		],
		"andre" : [
			215,195,170,
			225,205,170,
			230,185,160
		],
		"deniro" : [
			205,110,110,
			215,115,115,
			170, 80, 85,
			175, 75, 80,
			190, 90, 90
		],
		"familiar" : [
			140,130,160,
			125,120,145,
			160,150,170
		],
		"vitata" : [
			115, 80, 90,
			105, 70, 85,
			 70, 55, 80,
			 80, 60, 85,
			 60, 40, 65
		]
	}
}






